bitly_api_sdk-1.0.0.dist-info/licenses/LICENSE
bitlyapi/__init__.py
bitlyapi/api_helper.py
bitlyapi/bitlyapi_client.py
bitlyapi/configuration.py
bitlyapi/controllers/__init__.py
bitlyapi/controllers/base_controller.py
bitlyapi/controllers/bitlink_controller.py
bitlyapi/controllers/bitlinks_controller.py
bitlyapi/controllers/campaign_guid_controller.py
bitlyapi/controllers/campaigns_controller.py
bitlyapi/controllers/channel_guid_controller.py
bitlyapi/controllers/channels_controller.py
bitlyapi/controllers/clicks_controller.py
bitlyapi/controllers/custom_bitlink_controller.py
bitlyapi/controllers/custom_bitlinks_controller.py
bitlyapi/controllers/group_guid_controller.py
bitlyapi/controllers/groups_controller.py
bitlyapi/controllers/misc_controller.py
bitlyapi/controllers/organization_guid_controller.py
bitlyapi/controllers/organizations_controller.py
bitlyapi/controllers/preferences_controller.py
bitlyapi/controllers/user_controller.py
bitlyapi/controllers/webhook_guid_controller.py
bitlyapi/controllers/webhooks_controller.py
bitlyapi/exceptions/__init__.py
bitlyapi/exceptions/api_exception.py
bitlyapi/exceptions/badgateway_exception.py
bitlyapi/exceptions/badrequest_exception.py
bitlyapi/exceptions/conflict_exception.py
bitlyapi/exceptions/expectationfailed_exception.py
bitlyapi/exceptions/forbidden_exception.py
bitlyapi/exceptions/gone_exception.py
bitlyapi/exceptions/internalerror_exception.py
bitlyapi/exceptions/notfound_exception.py
bitlyapi/exceptions/temporarilyunavailable_exception.py
bitlyapi/exceptions/toomanyrequests_exception.py
bitlyapi/exceptions/unprocessableentity_exception.py
bitlyapi/exceptions/upgraderequired_exception.py
bitlyapi/http/__init__.py
bitlyapi/http/http_call_back.py
bitlyapi/http/http_method_enum.py
bitlyapi/http/http_request.py
bitlyapi/http/http_response.py
bitlyapi/http/auth/__init__.py
bitlyapi/http/auth/o_auth_2.py
bitlyapi/models/__init__.py
bitlyapi/models/add_custom_bitlink_request.py
bitlyapi/models/app_guid.py
bitlyapi/models/app_uri_path.py
bitlyapi/models/archived.py
bitly_api_sdk-1.0.0.dist-info/METADATA
bitly_api_sdk-1.0.0.dist-info/WHEEL
bitly_api_sdk-1.0.0.dist-info/top_level.txt
bitly_api_sdk-1.0.0.dist-info/RECORD
