Metadata-Version: 2.4
Name: bitly-api-sdk
Version: 1.0.0
Summary: The Bitly API provides programmatic access to URL shortening and link management services, enabling developers to create, manage, and analyze shortened links, campaigns, and organizations through authenticated REST endpoints.
Author-email: Muhammad Hamza Shahzad <muhammad.hamza@apimatic.io>
Project-URL: Documentation, https://docs.apimatic.io/
Requires-Python: >=3.7
License-File: LICENSE
Requires-Dist: apimatic-core>=0.2.20,~=0.2.0
Requires-Dist: apimatic-core-interfaces>=0.1.5,~=0.1.0
Requires-Dist: apimatic-requests-client-adapter>=0.1.6,~=0.1.0
Provides-Extra: testutils
Requires-Dist: pytest>=7.2.2; extra == "testutils"
Dynamic: license-file
